Metadata-Version: 2.1
Name: awsglue-local
Version: 1.0.2
Summary: Build Python interfaces to the AWS Glue ETL library for use as a local dependency.
Home-page: https://github.com/rpeloff/aws-glue-libs/tree/glue-1.0
Author: Ryan Eloff
Author-email: ryan.peter.eloff@gmail.com
Requires-Python: >=3,<3.8
Classifier: Programming Language :: Python :: 3
Classifier: Programming Language :: Python :: 3.4
Classifier: Programming Language :: Python :: 3.5
Classifier: Programming Language :: Python :: 3.6
Classifier: Programming Language :: Python :: 3.7
Requires-Dist: pyspark (>=2.2,<3.0)
Project-URL: Repository, https://github.com/rpeloff/aws-glue-libs/tree/glue-1.0
